vtissue/__init__.py
vtissue/run_training.py
vtissue/data/dataset.py
vtissue/data/graph_builder.py
vtissue/data/spatial.py
vtissue/data/spatial_weights.py
vtissue/inference/config.yaml
vtissue/inference/run_cell_type_prediction.py
vtissue/inference/run_expression_prediction.py
vtissue/inference/run_inference.py
vtissue/model/decoder.py
vtissue/model/encoder.py
vtissue/model/losses.py
vtissue/model/masking.py
vtissue/model/transformer.py
vtissue/perturbation/engine.py
vtissue/plotting/umap-spatial.py
vtissue/preprocessing/gene_mapping.py
vtissue/preprocessing/normalization.py
vtissue/preprocessing/pipeline.py
vtissue/preprocessing/preprocess.py
vtissue/resources/human_genome_GRCh38.p14.txt
vtissue/training/schedulers.py
vtissue/training/trainer.py
vtissue-0.1.10.dist-info/METADATA
vtissue-0.1.10.dist-info/WHEEL
vtissue-0.1.10.dist-info/RECORD
