Metadata-Version: 2.4
Name: vtissue
Version: 0.1.10
Summary: Self-Supervised Graph Transformer for Virtual Tissue Perturbation Modeling
Author-email: Ajit Johnson Nirmal <ajitjohnson.n@gmail.com>
Requires-Python: >=3.12
Requires-Dist: anndata>=0.12.6
Requires-Dist: numpy>=2.3.5
Requires-Dist: pandas>=2.3.3
Requires-Dist: psutil>=5.9.0
Requires-Dist: pyyaml>=6.0.3
Requires-Dist: scikit-learn>=1.0.0
Requires-Dist: scipy>=1.16.3
